RequestOn-0.0.3.dist-info/METADATA
RequestOn-0.0.3.dist-info/WHEEL
RequestOn-0.0.3.dist-info/RECORD
RequestOn-0.0.3.dist-info/metadata.json
RequestOn-0.0.3.dist-info/DESCRIPTION.rst
RequestOn-0.0.3.dist-info/entry_points.txt
RequestOn-0.0.3.dist-info/top_level.txt
requestOn/logs.py
requestOn/__init__.py
requestOn/request_service.py
requestOn/api.py
requestOn/__main__.py
requestOn/dashy.py
