Metadata-Version: 2.0
Name: RequestOn
Version: 0.0.3
Summary: Create and manage apps services requests with python
Home-page: https://github.com/nicolastrres/requestOn
Author: Nicolas Agustin Torres
Author-email: nicolastrres@gmail.com
License: MIT
Keywords: link checking development dashy requests status_codes
Platform: UNKNOWN
Classifier: Development Status :: 2 - Pre-Alpha
Classifier: Intended Audience :: Developers
Classifier: Topic :: Internet :: WWW/HTTP :: Site Management :: Link Checking
Classifier: License :: OSI Approved :: MIT License
Classifier: Programming Language :: Python :: 3
Classifier: Programming Language :: Python :: 3.2
Classifier: Programming Language :: Python :: 3.3
Classifier: Programming Language :: Python :: 3.4
